isahitlab/__about__.py
isahitlab/__init__.py
isahitlab/client.py
isahitlab/exceptions.py
isahitlab/log.py
isahitlab/actions/__init__.py
isahitlab/actions/base.py
isahitlab/actions/batch.py
isahitlab/actions/dataset.py
isahitlab/actions/integration.py
isahitlab/actions/project.py
isahitlab/actions/project_configuration.py
isahitlab/actions/task.py
isahitlab/actions/webhook.py
isahitlab/api/__init__.py
isahitlab/api/base.py
isahitlab/api/helpers.py
isahitlab/api/batch/__init__.py
isahitlab/api/batch/api.py
isahitlab/api/batch/mappers.py
isahitlab/api/data/__init__.py
isahitlab/api/data/api.py
isahitlab/api/dataset/__init__.py
isahitlab/api/dataset/api.py
isahitlab/api/dataset/mappers.py
isahitlab/api/file/__init__.py
isahitlab/api/file/api.py
isahitlab/api/integration/__init__.py
isahitlab/api/integration/api.py
isahitlab/api/integration/mappers.py
isahitlab/api/project/__init__.py
isahitlab/api/project/api.py
isahitlab/api/project/mappers.py
isahitlab/api/project_configuration/__init__.py
isahitlab/api/project_configuration/api.py
isahitlab/api/task/__init__.py
isahitlab/api/task/api.py
isahitlab/api/task/mappers.py
isahitlab/api/workflow/__init__.py
isahitlab/api/workflow/api.py
isahitlab/core/__init__.py
isahitlab/core/constants.py
isahitlab/core/http/__init__.py
isahitlab/core/http/auth.py
isahitlab/core/http/http_client.py
isahitlab/domain/__init__.py
isahitlab/domain/batch.py
isahitlab/domain/dataset.py
isahitlab/domain/export.py
isahitlab/domain/integration.py
isahitlab/domain/pagination.py
isahitlab/domain/project.py
isahitlab/domain/task.py
isahitlab/domain/workflow.py
isahitlab/formatters/__init__.py
isahitlab/formatters/base.py
isahitlab/formatters/kili_to_lab_formatter.py
isahitlab/formatters/lab_to_kili_formatter.py
isahitlab/formatters/lab_to_lab_formatter.py
isahitlab/formatters/lab_to_mask_formatter.py
isahitlab/formatters/lab_to_yolo_formatter.py
isahitlab/helpers/__init__.py
isahitlab/helpers/annotation.py
isahitlab/helpers/color.py
isahitlab-0.11.0.dist-info/METADATA
isahitlab-0.11.0.dist-info/WHEEL
isahitlab-0.11.0.dist-info/licenses/LICENSE.txt
isahitlab-0.11.0.dist-info/RECORD
